{
    "type": "fabric",
    "shadow_catchers": [
        "bodyShirt"
    ],
    "prefix": "collar",
    "included": {
        "King": ["collarKingSeam", "collarCatcher"],
        "Colorado": ["collarColoradoSeam", "collarCatcher"],
        "Cutaway": ["collarCutawaySeam", "collarCatcher"],
        "Kent": ["collarKentSeam", "collarCatcher"],
        "Windsor": ["collarWindsorSeam", "collarCatcher"],
        "Roma": ["collarRomaSeam", "collarCatcher"],
        "ColoradoMini": ["collarColoradoMiniSeam", "collarCatcher"],
        "VintageClub": ["collarVintageClubSeam", "collarCatcher"],
        "Londoner": ["collarLondonerSeam", "collarCatcher"],
        "VintageClubMini": ["collarVintageClubMiniSeam", "collarCatcher"]
    }, 
    "variants": [
        "King",
        "Cutaway",
        "Kent",
        "Windsor",
        "Roma",
        "Colorado",
        "ColoradoMini",
        "VintageClub",
        "Londoner",
        "VintageClubMini"
    ],
    "masks": {
        "King": [
            "collarKingInternalStand",
            "bodyShirtInternal"
        ],
        "Colorado": [
            "collarColoradoInternalStand",
            "bodyShirtInternal"
        ],
        "Cutaway": [
            "collarCutawayInternalStand",
            "bodyShirtInternal"
        ],
        "Kent": [
            "collarKentInternalStand",
            "bodyShirtInternal"
        ],
        "Windsor": [
            "collarWindsorInternalStand",
            "bodyShirtInternal"
        ],
        "Roma": [
            "collarRomaInternalStand",
            "bodyShirtInternal"
        ],
        "ColoradoMini": [
            "collarColoradoInternalStand",
            "bodyShirtInternal"
        ],
        "VintageClub": [
            "collarVintageInternalStand",
            "bodyShirtInternal"
        ],
        "Londoner": [
            "collarLondonerInternalStand",
            "bodyShirtInternal"
        ],
        "VintageClubMini": [
            "collarVintageInternalStand",
            "bodyShirtInternal"
        ]
    },
    "suffix": ""
}