{
    "type": "preset",
    "prefix": "preset_",
    "preset_id": "casual",
    "variants": [
        "casual"
    ],
    "suffix": "",
    "included": {
        "casual": [
            "bodyShirt",
            "bodyShirtInternal",
            "bodyShirtLogo",
            "bodyShirtStrings",
            "bodyShirtButton",
            "collarButtonDown",
            "collarButtonDownButton",
            "collarButtonDownSeam",
            "collarButtonDownExternalStand",
            "collarButtonDownInternalStand",
            "collarButtonDownSeamInternalStand",
            "collarButtonDownSeamSeamStand",
            "cuffTwoButtonsButton",
            "cuffTwoButtonsExternal",
            "cuffTwoButtonsInternal",
            "cuffTwoButtonsStrings",
            "pocket",
            "pocketStrings"
        ]
    },
    "button_texture": {
        "id": "SG2-1953",
        "texture": "C:/dev/blender_parser/textures/static/buttons/SG2-1953.png"
    },
    "label_texture": {
        "id" : "remark_birka",
        "texture": "C:/dev/blender_parser/textures/static/label/remark_birka.png"
    },
    "shadow_catchers": [],
    "masks": false
}